{
    "invalidClient": "Ваш клієнт невалідний! Будь ласка, використовуйте актуальний клієнт SurgeBrawl з офіційного сайту Football Brawl.",
    "maintenance": "Технічні роботи! Зайдіть пізніше!",
    "oldClient": "Ваш клієнт застарів! Будь ласка, використовуйте актуальний клієнт SurgeBrawl з офіційного сайту Football Brawl.",
    "newDevice": "Скоріше за все, у тебе новий пристрій. Зв'яжися з адміністраторами для переприв'язки.\n\nID НОВОГО ПРИСТРОЯ: \"{}\"\nТОКЕН: {}",
    "banned": "Причина бана: {}\n\nЯкщо ти вважаєш, що бан був помилковий, зв'яжися з адміністраторами.\n\nТОКЕН: {}",
    "maintenanceStarted": "На сервері почалися тех. роботи! Зайди пізніше!",
    "incorrectLogin": "Невалідність! Будь ласка, спробуй пізніше.",
    "error": "Виникла помилка! Спробуй перезайти!",
    "leavedBeforeBattleEnds": "Ти покинув минулу гру.\nТвої зароблені трофеї та токени згоріли!\nВ наступний раз не виходь с бою до його кінця!",
    "incorrectName": "Таке ім'я недопустимо!",
    "userGetError": "Помилка отримання інформації про гравця.",
    "ad_welcome": "Ласкаво просимо в SurgeBrawl!",
    "ad_didyouknow": "А ви знали, що маємо Telegram канал? Ні?\nПосилання: https://t.me/surgebrawl",
    "userClosedName": "ДАНИЙ ПРОФІЛЬ ЗАКРИТИЙ.\n{}",
    "noAccountInDB": "Відбулася помилка з базою даних!\nБудь ласка, зв'яжіться з адміністрацією або зітріть дані програми.\n\nDB Response: {}",
    "serverClosing": "Дякуємо вам за гру на SurgeBrawl!\nGG.",
    "months": ["Січень", "Лютий", "Березень", "Квітень", "Травень", "Червень", "Липень", "Серпень", "Вересень", "Жовтень", "Листопад", "Грудень"],
    "bans": {
        "exploiting": "Використання читів",
        "gemsExploiting": "Використання читів для накрутки валюти в грі.",
        "usingModifiedClient": "Використання модифікованого клієнта"
    },
    "offers": {
        "custom": "{}",
        "special": "ОСОБЛИВА АКЦІЯ!",
        "legendary": "ЛЕГЕНДАРНА АКЦІЯ!",
        "timeToPush": "Час грати!",
        "16update": "Нове оновлення!",
        "helloMonth": "Привіт, {}!",
        "byeMonth": "Прощавай, {}!",
        "wipe_1": "Вайп!",
        "wipe_2": "І ще за вайп!",
        "wipe_3": "Нену це вайп.",
        "1stApril": "З ПЕРШИМ КВІТНЯ!",
        "bard": "Акція від Барда!",
        "duelist": "Акція від Дуелянта!",
        "testOffer": "Тестова акція!",
        "middleOfMonth": "Середина місяця!",
        "freeMegabox": "Безкоштовна мегаскриня!",
        "projectsurgegift": "ProjectSurge!",
        "happybirthdayServer": "З Днем народження,",
        "happybirthdayServer_2": "SurgeBrawl!",
        "happybirthdayServer_3": "1 РІК!"
    },
    "gameroom": {
        "commands": {
            "help": "/команди",
            "monster": "/монстр"
        },
        "successInstalled": "Успішно встановлено!",
        "helpCommand": "Команди:\n/монстр - включити режим РОЗГРОМ СУПЕРСІТІ в геймруме.",
        "surgebothello": "Ласкаво просимо в геймруму.\nЯ - SurgeBot. Твій вірний помічник.\nНабери\"/команди\" щоб дізнатися про всі команди!"
    },
    "club": {
        "commands": {
            "stats": "/стата",
            "token": "/токен",
            "pro": "/про",
            "boxes": "/ящики",
            "theme": "/тема",
            "promo": "/промо",
            "link": "/link",
            "bonus": "/бонус",
            "help": "/команди",
            "prohelp": "/прокоманди",
            "closeprof": "/проф",
            "bptokens": "/бп",
            "patches": "/патч",
            "freeTheme": "/бтема"
        },
        "patchList": {
            "camera": "камера",
            "china": "китай",
            "slowmo": "слоумо",
            "mirror": "люстерко",
            "boss": "бос",
            "poison": "дим"
        },
        "serverStats": "Стата сервера:\nBuild version: 1.7 (for v28.189)\nТип сервера: prod\nЧас запуску: {}\nКількість зареєстрованих акаунтів: {}\nКількість ігрових кімнат: {}",
        "tokenMessage": "Твій токен: {}\nЗбережи токен! Ділитися токеном рекомендуємо тільки з адміністрацією проекту, в іншому випадку у вас є шанс втратити аккаунт",
        "installed": "Встановлено!",
        "proStatusDesc": "ПРО-СТАТУС.\nКоштує - 7.50 гривень.\nЗ ПРО-СТАТУСОМ ВИ ОТРИМУЄТЕ:\n\nКольоровий нікнейм!\nДодаткові кубки за гру! (2-4)\nДодаткові ресурси зі скринь (Х2)\nФОНИ ЗІ СТАРИХ ВЕРСІЙ?!\nЗнижки на акції!\nПодвоєнний щоденний бонус!\nДоступ до Преміального BrawlPass (БЕТА)\n\nУ тебе: {}",
        "havePro": ["НЕМАЄ PRO-СТАТУСУ", "Є PRO-СТАТУС"],
        "boxTokens": "У тебе:\n{} звичайних скринь. ({} Токенів)\n{} великих скринь. ({} Токенів)",
        "needProStatus": "Вам потрібен ПРО-СТАТУС!\nБольше інформації про ПРО-СТАТУС: /про",        
        "themeCommandInfo": "Зміна теми в головному меню!\n\n0. Звичайний\n1. Новий рік (2018)\n2. Місячний Новий Рік (2019)\n3. Clash Royale\n4. Лiто з Монстрами!\n5. Золота тиждень\n6. Ретрополіс\n7. Літо з роботами!\n8. Хеллоуїн\n9. Новий рік (2020)\n10. Місячний новий рік (2020)\n11. PSG (Футбол)\n12. 10 років Supercell\n13. Базар Тари\n14. Дефолтний (Літо з монстрами! Surge Edition)\n15. Старр Парк\n16. Місячний Фестиваль\n17. Чемпіонат\n18. Сноутель\n19. Сноутель (зі снігом)\n20. Старр Форс\n21. Рамадан\n22. Рік в китаї\n23. Літо з динозаврами!\n24. БЭД РЭНДОМС\n25. Ліс [SurgeBrawl]\n26. Хеллоуїн 2020\n27. Sun [SurgeBrawl]\n28. Winter [SurgeBrawl]\n29. Банда Золотий Руки!\n30. Рік тигра\n31. День неодруженого\n32. Місячний Новий Рік (2021)\n33. Золотий тиждень (2020)\n34. Золотий тиждень (2021)\n35. День народження SurgeBrawl (2022)\n\nІспользовать: /темa [0-35]",
        "done": "Готово!",
        "successInstalled": "Успішно встановлено!",
        "alreadyHaveProStatus": "Ви вже маєте ПРО-СТАТУС!",
        "forgotPromo": "Ви забули промокод!",
        "promoNotExist": "Такого промокоду немає!",
        "getPro": "Вітаємо з отриманням ПРО-СТАТУСУ!",
        "noRequests_outdated": "Поки немає заявок на прив'язку твого аккаунта",
        "linkSuccess_outdated": "Ви успішно прив'язали свій аккаунт до боту.",
        "linkNotSuccess_outdated": "Виникла помилка! Спробуй пізніше.",
        "comeLaterBonus": "Ще рано! Приходь {} по МСК!",
        "bonusGet": "Ти отримуєш {} токенов для ВЕЛИКОЇ СКРИНІ зі щоденного бонусу!",
        "helpCommand": "Команди клубу:\n/стата - статистика сервера\n/токен - ваш токен\n/про - Інформація про ПРО-СТАТУС\n/бтема - змінює фон безкоштовно на жовтий або фірмовий від SurgeBrawl\n/бокси - отримати інформацію про ящиках\n/прокоманди - команди для власників про-статусу!\n/бонус - отримати щоденний бонус.\n/промо [промо] - ввести промокод на ПРО-СТАТУС!",
        "proStatusHelp": "Команди для про-статусу:\n/тема - змінити фон в головному меню\n/проф - закрити/відкрити профіль\n/патч - кастомізувати свою гру",
        "surgebothello": "Ласкаво просимо до клубу! Я - SurgeBot! Твій вірний помічник!\nНабери\"/команди\" щоб дізнатися про всі команди!",
        "surgebotname": "SurgeBot",
        "thisClubDoesntExist": "Такого клубу немає!",
        "profileclosed": "Профіль успішно {}.",
        "profileclosedstatus": ["відкритий", "закритий"],
        "clubGetError": "Помилка отримання інформації про клуб.",
        "clubErrorName": "<c1>!ПОМИЛКА!</c>",
        "clubErrorDesc": "Ой, походу під час отримання інформації про клуб сталася неочікувана помилка!\nБудь ласка, спробуй ще раз. Якщо помилка не пройде, звернися до адміністраторів",
        "cannotChangeThemeCauseHalloween": "На жаль, не можна змінити тему під час ДНЯ НАРОДЖЕННЯ SURGEBRAWL!",
        "turnOnBrawlPassTokensGaining": "Ви успішно отримали {} токенів BrawlPass!",
        "turnstatuses": ["ввімкнули", "вимкнули"],
        "patchesInfo": "Патчі.\nЦе якийсь спосіб якось розважитися, якщо набридла звичайна гра.\nСписок доступних патчів:\n/патч китай - робить клієнт схожим на китайську\n/патч слоумо - уповільнює вашу гру (одна сесія)\n/патч камера (0-2) - встановити інші види камери.\n/патч люстерко - віддзеркалює всю карту.\n/патч бос - робить усі об'єкти босом. ламає логіку у 3 на 3. (одна сесія)\n/патч дим - додає дим у всі режими. ламає логіку бою (одна сесія)",
        "cameraPatchInfo": "Усі режими камери:\n0. Звичайний режим\n1. Зафіксований вигляд близько\n2. Вид зверху\nЗразок: /патч камера 1",
        "patchState": "Патч успішно {}",
        "turnedStates": ["увімкнено", "вимкнено", "перемикається"],
        "noCommand": "Такої команди немає!\nВведіть /команди для отримання команд!"
    },
    "inbox": [
        "Ласкаво просимо на SurgeBrawl!",
        "ОНОВЛЕННЯ ВІД 18.10.21 (#1)\nПерепісані лідерборди.\nТеперь кожні 3 тижні буде відбуватися скидання сезону.\nПромокоди можна тепер вводити в \"Коді автора\"\nБула розроблена клубна пошта.\nВідремонтовано підвищення/пониження/кік учасника\nКоманда /монстр була перенесена в геймрум-бота",
        "ОНОВЛЕННЯ ВІД 18.10.21 (#2)\nТеперь з ПРО-СТАТУСОМ можна закривати свою статистику! (КОМАНДА /ПРОФ В КЛУБІ)\nТакже по приколу був введений чат в геймрумах.\nОтремонтіровано отримання старпоінтов.\nБув доданий лідерборд клубів.\nТепер ви можете отримати трофейних бравлеров з магазину після досягнення їх числа.",
        "ОНОВЛЕННЯ ВІД 11.09.21:\nПокращена система безпеки акаунтів\nПокращені акції.\nТеперь скіни необхідно вибивати з ящиків.\nДодан переклад на англійську і українську мову.\nТеперь раз на годину змінюються карти.",
        "ОНОВЛЕННЯ КЛІЄНТА ВІД 22.08.21:\nТеперь кнопка \"Грати\" переносить вас ВІДРАЗУ В ГРУ!\nДодана ​​корисна інформація зліва зверху (близько трофейної дороги)\nДобавлени 2 нових фону для ПРО-СТАТУСУ!",
        "ОНОВЛЕННЯ ВІД 19.08.21:\nТеперь можна подивитися коли був користувач онлайн в клубі.\nГра буде попереджати вас за 5 хвилин до тех. робіт.\nДодана ​​система промокодів.",
        "ОНОВЛЕННЯ ВІД 25.07.21:\nПрі натисканні на кнопку Грати, вас перекидає в геймруму."
    ]
}